{
  "global": {
    "color": {
      "blue100": {
        "value": "#228ddb",
        "type": "color"
      },
      "blue200": {
        "value": "#1575bb",
        "type": "color"
      },
      "blue300": {
        "value": "#11619b",
        "type": "color"
      },
      "blue400": {
        "value": "#0e4f7e",
        "type": "color"
      },
      "blue500": {
        "value": "#0b3d61",
        "type": "color"
      }
    },
    "elevation": {
      "sombra100": {
        "value": {
          "color": "#00000073",
          "type": "dropShadow",
          "x": 0,
          "y": 4,
          "blur": 14,
          "spread": 0
        },
        "type": "boxShadow"
      },
      "sombra200": {
        "value": {
          "color": "#00000073",
          "type": "dropShadow",
          "x": 0,
          "y": 4,
          "blur": 24,
          "spread": 0
        },
        "type": "boxShadow"
      },
      "sombra50": {
        "value": {
          "color": "#00000059",
          "type": "dropShadow",
          "x": 0,
          "y": 4,
          "blur": 8,
          "spread": 0
        },
        "type": "boxShadow"
      }
    },
    "fontFamilies": {
      "inter": {
        "value": "Inter",
        "type": "fontFamilies"
      }
    },
    "lineHeights": {
      "0": {
        "value": "AUTO",
        "type": "lineHeights"
      }
    },
    "fontWeights": {
      "inter-0": {
        "value": "Medium",
        "type": "fontWeights"
      },
      "inter-1": {
        "value": "Regular",
        "type": "fontWeights"
      },
      "inter-2": {
        "value": "Light",
        "type": "fontWeights"
      }
    },
    "fontSize": {
      "0": {
        "value": "16",
        "type": "fontSizes"
      },
      "1": {
        "value": "22",
        "type": "fontSizes"
      },
      "2": {
        "value": "32",
        "type": "fontSizes"
      }
    },
    "letterSpacing": {
      "0": {
        "value": "0%",
        "type": "letterSpacing"
      }
    },
    "paragraphSpacing": {
      "0": {
        "value": "0",
        "type": "paragraphSpacing"
      }
    },
    "text": {
      "titular": {
        "value": {
          "fontFamily": "{fontFamilies.inter}",
          "fontWeight": "{fontWeights.inter-0}",
          "lineHeight": "{lineHeights.0}",
          "fontSize": "{fontSize.2}",
          "letterSpacing": "{letterSpacing.0}",
          "paragraphSpacing": "{paragraphSpacing.0}",
          "paragraphIndent": "{paragraphIndent.0}",
          "textCase": "{textCase.none}",
          "textDecoration": "{textDecoration.none}"
        },
        "type": "typography"
      },
      "H1": {
        "value": {
          "fontFamily": "{fontFamilies.inter}",
          "fontWeight": "{fontWeights.inter-1}",
          "lineHeight": "{lineHeights.0}",
          "fontSize": "{fontSize.1}",
          "letterSpacing": "{letterSpacing.0}",
          "paragraphSpacing": "{paragraphSpacing.0}",
          "paragraphIndent": "{paragraphIndent.0}",
          "textCase": "{textCase.none}",
          "textDecoration": "{textDecoration.none}"
        },
        "type": "typography"
      },
      "body": {
        "value": {
          "fontFamily": "{fontFamilies.inter}",
          "fontWeight": "{fontWeights.inter-2}",
          "lineHeight": "{lineHeights.0}",
          "fontSize": "{fontSize.0}",
          "letterSpacing": "{letterSpacing.0}",
          "paragraphSpacing": "{paragraphSpacing.0}",
          "paragraphIndent": "{paragraphIndent.0}",
          "textCase": "{textCase.none}",
          "textDecoration": "{textDecoration.none}"
        },
        "type": "typography"
      }
    },
    "textCase": {
      "none": {
        "value": "none",
        "type": "textCase"
      }
    },
    "textDecoration": {
      "none": {
        "value": "none",
        "type": "textDecoration"
      }
    },
    "paragraphIndent": {
      "0": {
        "value": "0px",
        "type": "dimension"
      }
    }
  },
  "$themes": [],
  "$metadata": {
    "tokenSetOrder": [
      "global"
    ]
  }
}